grepmap/__init__.py
grepmap/diagnostics.py
grepmap/discovery.py
grepmap/facade.py
grepmap/cache/__init__.py
grepmap/cache/manager.py
grepmap/core/__init__.py
grepmap/core/config.py
grepmap/core/types.py
grepmap/extraction/__init__.py
grepmap/extraction/fields.py
grepmap/extraction/markdown.py
grepmap/extraction/parser.py
grepmap/extraction/signatures.py
grepmap/ranking/__init__.py
grepmap/ranking/boosts.py
grepmap/ranking/bridges.py
grepmap/ranking/callers.py
grepmap/ranking/confidence.py
grepmap/ranking/focus.py
grepmap/ranking/git_weight.py
grepmap/ranking/intent.py
grepmap/ranking/optimizer.py
grepmap/ranking/pagerank.py
grepmap/ranking/story.py
grepmap/ranking/surface.py
grepmap/ranking/symbols.py
grepmap/ranking/temporal.py
grepmap/rendering/__init__.py
grepmap/rendering/base.py
grepmap/rendering/clusters.py
grepmap/rendering/directory.py
grepmap/rendering/stats.py
grepmap/rendering/syntax.py
grepmap/rendering/tree.py
grepmap/visualization/__init__.py
grepmap/visualization/__main__.py
grepmap/visualization/cli.py
grepmap/visualization/exporter.py
grepmap/visualization/server.py
grepmap/visualization/tuner.py
grepmap-2.0.0.dist-info/METADATA
grepmap-2.0.0.dist-info/WHEEL
grepmap-2.0.0.dist-info/entry_points.txt
grepmap-2.0.0.dist-info/licenses/LICENSE
grepmap-2.0.0.dist-info/RECORD
