Metadata-Version: 2.4
Name: grepmap
Version: 2.0.0
Summary: AI-powered codebase navigator using PageRank and tree-sitter
Project-URL: Homepage, https://github.com/holo-q/grepmap/
Project-URL: Repository, https://github.com/holo-q/grepmap
Project-URL: Issues, https://github.com/holo-q/grepmap/issues
Author: holo-q
License-Expression: MIT
License-File: LICENSE
Keywords: ai,code-navigation,llm,mcp,pagerank,tree-sitter
Classifier: Development Status :: 4 - Beta
Classifier: Intended Audience :: Developers
Classifier: Programming Language :: Python :: 3
Classifier: Programming Language :: Python :: 3.11
Classifier: Programming Language :: Python :: 3.12
Classifier: Programming Language :: Python :: 3.13
Classifier: Topic :: Software Development :: Libraries :: Python Modules
Classifier: Topic :: Text Processing :: Linguistic
Requires-Python: >=3.11
Requires-Dist: diskcache>=5.6.0
Requires-Dist: fastmcp>=2.11.3
Requires-Dist: grep-ast>=0.3.0
Requires-Dist: networkx>=3.0
Requires-Dist: numpy>=1.24.0
Requires-Dist: pygments>=2.14.0
Requires-Dist: rich>=13.0.0
Requires-Dist: scipy>=1.10.0
Requires-Dist: tiktoken>=0.5.0
Requires-Dist: tree-sitter>=0.20.0
Provides-Extra: dev
Requires-Dist: testslide>=2.7.0; extra == 'dev'
